recursive_package/__init__.py
recursive_package/recursive_call.py
recursive_package-0.1.0.dist-info/LICENSE
recursive_package-0.1.0.dist-info/WHEEL
recursive_package-0.1.0.dist-info/METADATA
recursive_package-0.1.0.dist-info/RECORD
