Metadata-Version: 2.1
Name: recursive_package
Version: 0.1.0
Summary: Awesome recursive package, uninstall flit_callable latter
Home-page: https://github.com
License: UNKNOWN
Author: xichen3
Author-email: xichen3@microsoft.com
Classifier: License :: OSI Approved :: MIT License
